dynonet/__init__.py
dynonet/filtering.py
dynonet/functional.py
dynonet/lti.py
dynonet/metrics.py
dynonet/static.py
dynonet-0.1.2.dist-info/LICENSE
dynonet-0.1.2.dist-info/METADATA
dynonet-0.1.2.dist-info/WHEEL
dynonet-0.1.2.dist-info/top_level.txt
dynonet-0.1.2.dist-info/RECORD
