Metadata-Version: 2.1
Name: dynonet
Version: 0.1.2
Summary: dynoNet: A neural network architecture for learning dynamical systems
Home-page: https://github.com/forgi86/dynonet
Author: Marco Forgione and Dario Piga
Author-email: marco.forgione1986@gmail.com
License: MIT
Project-URL: Bug Tracker, https://github.com/forgi86/dynonet/issues
Classifier: License :: OSI Approved :: MIT License
Classifier: Operating System :: OS Independent
Classifier: Programming Language :: Python :: 3.7
Classifier: Development Status :: 4 - Beta
Classifier: Environment :: Console
Classifier: Intended Audience :: Developers
Classifier: Intended Audience :: Education
Classifier: Intended Audience :: Science/Research
Classifier: Topic :: Scientific/Engineering
License-File: LICENSE
Requires-Dist: numpy >=1.19.4
Requires-Dist: scipy >=1.5.4
Requires-Dist: matplotlib >=3.3.3
Requires-Dist: pandas >=1.1.4
Requires-Dist: torch >=1.4
